smanalytics/__init__.py
smanalytics/main.py
smanalytics-2.8.dist-info/METADATA
smanalytics-2.8.dist-info/WHEEL
smanalytics-2.8.dist-info/top_level.txt
smanalytics-2.8.dist-info/RECORD
