Metadata-Version: 2.1
Name: smanalytics
Version: 2.8
Summary: Analytics library for Social Media
Author-email: smanalytics@gmail.com
